numquad/__init__.py
numquad/_cli.py
numquad/_exception.py
numquad/_optimize.py
numquad/_scipy_compat.py
numquad/c1/__init__.py
numquad/c1/_adaptive.py
numquad/c1/_chebyshev_gauss.py
numquad/c1/_clenshaw_curtis.py
numquad/c1/_fejer.py
numquad/c1/_gauss_jacobi.py
numquad/c1/_gauss_kronrod.py
numquad/c1/_gauss_legendre.py
numquad/c1/_gauss_lobatto.py
numquad/c1/_gauss_patterson.py
numquad/c1/_gauss_radau.py
numquad/c1/_helpers.py
numquad/c1/_midpoint.py
numquad/c1/_newton_cotes.py
numquad/c1/_trapezoidal.py
numquad/c2/__init__.py
numquad/c2/_albrecht_collatz.py
numquad/c2/_burnside.py
numquad/c2/_cohen_gismalla.py
numquad/c2/_franke.py
numquad/c2/_hammer_stroud.py
numquad/c2/_helpers.py
numquad/c2/_irwin.py
numquad/c2/_maxwell.py
numquad/c2/_meister.py
numquad/c2/_miller.py
numquad/c2/_phillips.py
numquad/c2/_product.py
numquad/c2/_stroud.py
numquad/c2/_tyler.py
numquad/c2/_waldron.py
numquad/c2/_cools_haegemans_1985/__init__.py
numquad/c2/_cools_haegemans_1985/cools_haegemans_1985_09_1.json
numquad/c2/_cools_haegemans_1985/cools_haegemans_1985_13_1.json
numquad/c2/_cools_haegemans_1985/cools_haegemans_1985_13_2.json
numquad/c2/_cools_haegemans_1985/cools_haegemans_1985_13_3.json
numquad/c2/_cools_haegemans_1985/cools_haegemans_1985_17_1.json
numquad/c2/_cools_haegemans_1985/cools_haegemans_1985_17_2.json
numquad/c2/_cools_haegemans_1988/__init__.py
numquad/c2/_cools_haegemans_1988/cools_haegemans_1988_1.json
numquad/c2/_cools_haegemans_1988/cools_haegemans_1988_2.json
numquad/c2/_dunavant/__init__.py
numquad/c2/_dunavant/dunavant_04.json
numquad/c2/_dunavant/dunavant_05.json
numquad/c2/_dunavant/dunavant_06.json
numquad/c2/_dunavant/dunavant_07.json
numquad/c2/_dunavant/dunavant_08.json
numquad/c2/_dunavant/dunavant_09.json
numquad/c2/_dunavant/dunavant_10.json
numquad/c2/_haegemans_piessens/__init__.py
numquad/c2/_haegemans_piessens/haegemans_piessens.json
numquad/c2/_morrow_patterson/__init__.py
numquad/c2/_morrow_patterson/morrow_patterson_1.json
numquad-0.16.10.dist-info/LICENSE
numquad-0.16.10.dist-info/METADATA
numquad-0.16.10.dist-info/WHEEL
numquad-0.16.10.dist-info/entry_points.txt
numquad-0.16.10.dist-info/top_level.txt
numquad-0.16.10.dist-info/RECORD
